README.md
setup.cfg
setup.py
BinomGauss_distros/Binomialdistribution.py
BinomGauss_distros/Gaussiandistribution.py
BinomGauss_distros/Generaldistribution.py
BinomGauss_distros/__init__.py
BinomGauss_distros.egg-info/PKG-INFO
BinomGauss_distros.egg-info/SOURCES.txt
BinomGauss_distros.egg-info/dependency_links.txt
BinomGauss_distros.egg-info/not-zip-safe
BinomGauss_distros.egg-info/top_level.txt